fotoobo/__init__.py
fotoobo/cli/__init__.py
fotoobo/cli/cloud/__init__.py
fotoobo/cli/cloud/asset/__init__.py
fotoobo/cli/cloud/asset/asset.py
fotoobo/cli/cloud/asset/get.py
fotoobo/cli/cloud/cloud.py
fotoobo/cli/convert.py
fotoobo/cli/ems/__init__.py
fotoobo/cli/ems/ems.py
fotoobo/cli/ems/get.py
fotoobo/cli/ems/monitor.py
fotoobo/cli/faz/__init__.py
fotoobo/cli/faz/faz.py
fotoobo/cli/faz/get.py
fotoobo/cli/fgt/__init__.py
fotoobo/cli/fgt/config.py
fotoobo/cli/fgt/fgt.py
fotoobo/cli/fgt/get/__init__.py
fotoobo/cli/fgt/get/cmdb/__init__.py
fotoobo/cli/fgt/get/cmdb/cmdb.py
fotoobo/cli/fgt/get/cmdb/firewall/__init__.py
fotoobo/cli/fgt/get/cmdb/firewall/firewall.py
fotoobo/cli/fgt/get/get.py
fotoobo/cli/fgt/monitor.py
fotoobo/cli/fmg/__init__.py
fotoobo/cli/fmg/fmg.py
fotoobo/cli/fmg/get.py
fotoobo/cli/get.py
fotoobo/cli/main.py
fotoobo/exceptions/__init__.py
fotoobo/exceptions/exceptions.py
fotoobo/fortinet/__init__.py
fotoobo/fortinet/convert.py
fotoobo/fortinet/fortianalyzer.py
fotoobo/fortinet/forticlientems.py
fotoobo/fortinet/forticloudasset.py
fotoobo/fortinet/fortigate.py
fotoobo/fortinet/fortigate_config.py
fotoobo/fortinet/fortigate_config_check.py
fotoobo/fortinet/fortigate_info.py
fotoobo/fortinet/fortimanager.py
fotoobo/fortinet/fortinet.py
fotoobo/helpers/__init__.py
fotoobo/helpers/cli.py
fotoobo/helpers/config.py
fotoobo/helpers/files.py
fotoobo/helpers/log.py
fotoobo/helpers/output.py
fotoobo/helpers/result.py
fotoobo/helpers/vault.py
fotoobo/inventory/__init__.py
fotoobo/inventory/generic.py
fotoobo/inventory/inventory.py
fotoobo/main.py
fotoobo/tools/__init__.py
fotoobo/tools/cloud/__init__.py
fotoobo/tools/cloud/asset/__init__.py
fotoobo/tools/cloud/asset/get.py
fotoobo/tools/convert.py
fotoobo/tools/ems/__init__.py
fotoobo/tools/ems/get.py
fotoobo/tools/ems/monitor.py
fotoobo/tools/faz/__init__.py
fotoobo/tools/faz/get.py
fotoobo/tools/fcasset/__init__.py
fotoobo/tools/fgt/__init__.py
fotoobo/tools/fgt/cmdb/__init__.py
fotoobo-3.0.0.dist-info/LICENSE
fotoobo-3.0.0.dist-info/METADATA
fotoobo-3.0.0.dist-info/WHEEL
fotoobo-3.0.0.dist-info/entry_points.txt
fotoobo-3.0.0.dist-info/RECORD
