Metadata-Version: 2.3
Name: fotoobo
Version: 3.0.0
Summary: The awesome Fortinet Toolbox
License: LGPL-3.0-only
Author: Patrik Spiess
Author-email: patrik.spiess@mgb.ch
Requires-Python: >=3.9.0,<4
Classifier: Framework :: Pytest
Classifier: Framework :: Sphinx
Classifier: Framework :: Sphinx :: Extension
Classifier: Framework :: Sphinx :: Theme
Classifier: Framework :: tox
Classifier: Intended Audience :: Developers
Classifier: Intended Audience :: Information Technology
Classifier: Intended Audience :: System Administrators
Classifier: Intended Audience :: Telecommunications Industry
Classifier: License :: OSI Approved :: GNU Lesser General Public License v3 (LGPLv3)
Classifier: Natural Language :: English
Classifier: Operating System :: POSIX :: Linux
Classifier: Operating System :: Unix
Classifier: Programming Language :: Python :: 3
Classifier: Programming Language :: Python :: 3.9
Classifier: Programming Language :: Python :: 3.10
Classifier: Programming Language :: Python :: 3.11
Classifier: Programming Language :: Python :: 3.12
Classifier: Programming Language :: Python :: 3.13
Classifier: Topic :: Security
Classifier: Topic :: System :: Networking
Classifier: Topic :: System :: Networking :: Firewalls
Classifier: Topic :: System :: Networking :: Monitoring
Classifier: Topic :: System :: Systems Administration
Requires-Dist: Jinja2
Requires-Dist: PyYAML
Requires-Dist: requests
Requires-Dist: rich
Requires-Dist: typer (>=0.15,<0.16)
Project-URL: Repository, https://github.com/migros/fotoobo
